figgy/__init__.py
figgy/fig_store.py
figgy/fig_svc.py
figgy/figs.py
figgy/utils.py
figgy/writer.py
figgy_lib-1.0.0.dist-info/METADATA
figgy_lib-1.0.0.dist-info/WHEEL
figgy_lib-1.0.0.dist-info/top_level.txt
figgy_lib-1.0.0.dist-info/RECORD
