Metadata-Version: 2.1
Name: figgy-lib
Version: 1.0.0
Summary: Python library that supports Python development while using the Figgy config management framework: https://www.figgy.dev
Home-page: https://www.figgy.dev
Author: Jordan Mance
Author-email: jordan@figgy.dev
License: UNKNOWN
Platform: UNKNOWN
Classifier: Programming Language :: Python :: 3
Classifier: Intended Audience :: Developers
Classifier: License :: OSI Approved :: MIT License
Classifier: Operating System :: OS Independent
Classifier: Natural Language :: English
Classifier: Programming Language :: Python :: 3.5
Classifier: Programming Language :: Python :: 3.6
Classifier: Programming Language :: Python :: 3.7
Classifier: Programming Language :: Python :: Implementation
Requires-Python: >=3.6
Requires-Dist: boto3 (>=1.13.0)
